requests_safe/__init__.py
requests_safe-0.2.dist-info/LICENSE
requests_safe-0.2.dist-info/METADATA
requests_safe-0.2.dist-info/WHEEL
requests_safe-0.2.dist-info/top_level.txt
requests_safe-0.2.dist-info/RECORD
