Metadata-Version: 2.1
Name: requests-safe
Version: 0.2
Summary: Provides an adapter for requests that won't allow connections to "unsafe" networks.
Home-page: https://github.com/crunch-io/requests-safe
Author: Bert JW Regeer
Author-email: bertjw@regeer.org
License: ISC License
Keywords: requests,urllib3
Platform: UNKNOWN
Classifier: Programming Language :: Python :: 2
Classifier: Programming Language :: Python :: 2.7
Classifier: Programming Language :: Python :: 3
Classifier: Programming Language :: Python :: 3.5
Classifier: Programming Language :: Python :: 3.6
Classifier: Programming Language :: Python :: 3.7
Requires-Dist: requests
Requires-Dist: urllib3
Requires-Dist: ipaddress ; python_version == "2.7"
Provides-Extra: testing
Requires-Dist: pytest ; extra == 'testing'
Requires-Dist: pytest-cov ; extra == 'testing'
Requires-Dist: coverage ; extra == 'testing'
Requires-Dist: mocket ; extra == 'testing'
